<annotation>
	<folder>JPEGImages</folder>
	<filename>000251.jpg</filename>
	<path>C:\Users\ASUS\Desktop\数据集\JPEGImages\000251.jpg</path>
	<source>
		<database>Unknown</database>
	</source>
	<size>
		<width>1920</width>
		<height>1080</height>
		<depth>3</depth>
	</size>
	<segmented>0</segmented>
	<object>
		<name>arrow</name>
		<pose>Unspecified</pose>
		<truncated>0</truncated>
		<difficult>0</difficult>
		<bndbox>
			<xmin>414</xmin>
			<ymin>693</ymin>
			<xmax>965</xmax>
			<ymax>836</ymax>
		</bndbox>
	</object>
	<object>
		<name>arrowFront</name>
		<pose>Unspecified</pose>
		<truncated>0</truncated>
		<difficult>0</difficult>
		<bndbox>
			<xmin>870</xmin>
			<ymin>777</ymin>
			<xmax>968</xmax>
			<ymax>839</ymax>
		</bndbox>
	</object>
</annotation>
