<annotation>
	<folder>JPEGImages</folder>
	<filename>000142.jpg</filename>
	<path>C:\Users\ASUS\Desktop\数据集\JPEGImages\000142.jpg</path>
	<source>
		<database>Unknown</database>
	</source>
	<size>
		<width>4032</width>
		<height>3024</height>
		<depth>3</depth>
	</size>
	<segmented>0</segmented>
	<object>
		<name>arrow</name>
		<pose>Unspecified</pose>
		<truncated>0</truncated>
		<difficult>0</difficult>
		<bndbox>
			<xmin>1008</xmin>
			<ymin>993</ymin>
			<xmax>1868</xmax>
			<ymax>1573</ymax>
		</bndbox>
	</object>
	<object>
		<name>arrow</name>
		<pose>Unspecified</pose>
		<truncated>0</truncated>
		<difficult>0</difficult>
		<bndbox>
			<xmin>1715</xmin>
			<ymin>1470</ymin>
			<xmax>3256</xmax>
			<ymax>2783</ymax>
		</bndbox>
	</object>
	<object>
		<name>arrowFront</name>
		<pose>Unspecified</pose>
		<truncated>0</truncated>
		<difficult>0</difficult>
		<bndbox>
			<xmin>2891</xmin>
			<ymin>2466</ymin>
			<xmax>3256</xmax>
			<ymax>2781</ymax>
		</bndbox>
	</object>
	<object>
		<name>arrowFront</name>
		<pose>Unspecified</pose>
		<truncated>0</truncated>
		<difficult>0</difficult>
		<bndbox>
			<xmin>1016</xmin>
			<ymin>1472</ymin>
			<xmax>1134</xmax>
			<ymax>1575</ymax>
		</bndbox>
	</object>
</annotation>
